{"ip": "39.137.95.74", "port": "8990", "schema": "http", "update_time": "2020-03-10 01:22:25", "original": "\u65e0\u5fe7\u4ee3\u7406"}
{"ip": "101.4.136.34", "port": "8618", "schema": "http", "update_time": "2020-03-10 01:22:25", "original": "\u65e0\u5fe7\u4ee3\u7406"}
{"ip": "39.137.69.7", "port": "8186", "schema": "http", "update_time": "2020-03-10 01:22:25", "original": "\u65e0\u5fe7\u4ee3\u7406"}
{"ip": "221.180.170.104", "port": "8226", "schema": "http", "update_time": "2020-03-10 01:22:25", "original": "\u65e0\u5fe7\u4ee3\u7406"}
